neuron/hclass3.py
neuron/expect_hocerr.py
neuron/psection.py
neuron/config.py
neuron/units.py
neuron/sections.py
neuron/__init__.py
neuron/_config_params.py
neuron/hoc.cpython-312-darwin.so
neuron/coreneuron.py
neuron/doc.py
neuron/help_data.dat
neuron/gui.py
neuron/nonvint_block_supervisor.py
neuron/neuroml/metadata.py
neuron/neuroml/morphml.py
neuron/neuroml/xml2nrn.py
neuron/neuroml/__init__.py
neuron/neuroml/neuroml.py
neuron/neuroml/rdxml.py
neuron/neuroml/biophysics.py
neuron/rxd/rxdException.py
neuron/rxd/options.py
neuron/rxd/plugins.py
neuron/rxd/rxdsection.py
neuron/rxd/species.py
neuron/rxd/rxdmath.py
neuron/rxd/rate.py
neuron/rxd/region.py
neuron/rxd/multiCompartmentReaction.py
neuron/rxd/constants.py
neuron/rxd/dimension3.py
neuron/rxd/__init__.py
neuron/rxd/section1d.py
neuron/rxd/export.py
neuron/rxd/initializer.py
neuron/rxd/rangevar.py
neuron/rxd/geometry.py
neuron/rxd/rxd.py
neuron/rxd/generalizedReaction.py
neuron/rxd/nodelist.py
neuron/rxd/node.py
neuron/rxd/gui.py
neuron/rxd/reaction.py
neuron/rxd/geometry3d/simplevolume_helper.py
neuron/rxd/geometry3d/ctng.cpython-312-darwin.so
neuron/rxd/geometry3d/GeneralizedVoxelization.py
neuron/rxd/geometry3d/FullJoinMorph.py
neuron/rxd/geometry3d/scalarField.py
neuron/rxd/geometry3d/__init__.py
neuron/rxd/geometry3d/surface_a.py
neuron/rxd/geometry3d/surfaces.cpython-312-darwin.so
neuron/rxd/geometry3d/triangularMesh.py
neuron/rxd/geometry3d/voxelize.py
neuron/rxd/geometry3d/voxelize2.py
neuron/rxd/geometry3d/surface.py
neuron/rxd/geometry3d/graphicsPrimitives.cpython-312-darwin.so
neuron/nmodl/dsl.py
neuron/nmodl/symtab.py
neuron/nmodl/_nmodl.cpython-312-darwin.so
neuron/nmodl/__init__.py
neuron/nmodl/visitor.py
neuron/nmodl/ast.py
neuron/nmodl/ode.py
neuron/nmodl/ext/example/passive.mod
neuron/nmodl/ext/example/expsyn.mod
neuron/nmodl/ext/example/exp2syn.mod
neuron/nmodl/ext/example/hh.mod
neuron/nmodl/ext/viz/index.html
neuron-9.0.1.dist-info/RECORD
neuron-9.0.1.dist-info/WHEEL
neuron-9.0.1.dist-info/METADATA
neuron-9.0.1.dist-info/licenses/Copyright
