Metadata-Version: 2.2
Name: neuron
Version: 9.0.1
Summary: Empirically-based simulator for modeling neurons and networks of neurons
Author: Yale, Blue Brain Project
Author-Email: Michael Hines <michael.hines@yale.edu>
Maintainer: Michael Hines
License: Copyright (c) 2018, Michael Hines
Classifier: License :: Other/Proprietary License
Classifier: Programming Language :: C++
Classifier: Programming Language :: Python
Classifier: Programming Language :: Python :: 3 :: Only
Classifier: Programming Language :: Python :: 3.9
Classifier: Programming Language :: Python :: 3.10
Classifier: Programming Language :: Python :: 3.11
Classifier: Programming Language :: Python :: 3.12
Classifier: Programming Language :: Python :: 3.13
Classifier: Topic :: Scientific/Engineering
Project-URL: source, https://github.com/neuronsimulator/nrn
Project-URL: website, https://neuron.yale.edu/neuron/
Requires-Python: >=3.9
Requires-Dist: find-libpython
Requires-Dist: numpy>=1.9.3
Requires-Dist: packaging>=22.0
Requires-Dist: setuptools
Requires-Dist: sympy>=1.3
